ClastEngine/__init__.py
ClastEngine/main.py
ClastEngine/test_game.py
ClastEngine-0.5.6.dist-info/LICENSE
ClastEngine-0.5.6.dist-info/METADATA
ClastEngine-0.5.6.dist-info/WHEEL
ClastEngine-0.5.6.dist-info/top_level.txt
ClastEngine-0.5.6.dist-info/RECORD
