Metadata-Version: 2.1
Name: ClastEngine
Version: 0.5.6
Summary: Простой 2D движок для создания простых игр.
Home-page: UNKNOWN
Author-email: romanhaziahmetov3@gmail.com
License: UNKNOWN
Platform: UNKNOWN
License-File: LICENSE
Requires-Dist: keyboard
